dataclass_alias/__init__.py
dataclass_alias/alias.py
dataclass_alias-0.1.0.dist-info/LICENSE
dataclass_alias-0.1.0.dist-info/METADATA
dataclass_alias-0.1.0.dist-info/WHEEL
dataclass_alias-0.1.0.dist-info/RECORD
